README.md
setup.py
Image_Recoz_NeuralNet.egg-info/PKG-INFO
Image_Recoz_NeuralNet.egg-info/SOURCES.txt
Image_Recoz_NeuralNet.egg-info/dependency_links.txt
Image_Recoz_NeuralNet.egg-info/entry_points.txt
Image_Recoz_NeuralNet.egg-info/requires.txt
Image_Recoz_NeuralNet.egg-info/top_level.txt
simple_neuralnet/__init__.py