Metadata-Version: 1.2
Name: Image-Recoz-NeuralNet
Version: 0.1
Summary: A simple neural network library with UI for training and recognition
Home-page: UNKNOWN
Author: Sai Mounik
License: UNKNOWN
Platform: UNKNOWN
Requires-Python: >=3.9
